hacktor/__init__.py
hacktor/dtx/__init__py
hacktor/dtx/evaluator.py
hacktor/dtx/generator.py
hacktor/dtx/parser.py
hacktor/dtx/scanner.py
hacktor/main.py
hacktor/models/__init__.py
hacktor/models/base.py
hacktor/models/exceptions.py
hacktor/models/groq.py
hacktor/models/hf.py
hacktor/models/openai.py
hacktor/models/utils.py
hacktor/models/wrapper.py
hacktor/utils/__init__.py
hacktor/utils/printer.py
hacktor/webapp/__init__.py
hacktor/webapp/ai/parser.py
hacktor/webapp/ai/predict.py
hacktor/webapp/burp.py
hacktor/webapp/crawler.py
hacktor/webapp/fuzzer.py
hacktor/webapp/gradio.py
hacktor/webapp/har.py
hacktor/webapp/model.py
hacktor/webapp/playwright.py
hacktor/workflow/__init__.py
hacktor/workflow/phases.py
hacktor/workflow/scanner.py
hacktor-0.8.0.dist-info/LICENSE
hacktor-0.8.0.dist-info/METADATA
hacktor-0.8.0.dist-info/WHEEL
hacktor-0.8.0.dist-info/entry_points.txt
hacktor-0.8.0.dist-info/RECORD
