Metadata-Version: 2.1
Name: hacktor
Version: 0.8.0
Summary: LLM models Red Teaming Utility Package
Author: jchauhan
Author-email: jitendra@detoxio.ai
Requires-Python: >=3.10,<4.0
Classifier: Programming Language :: Python :: 3
Classifier: Programming Language :: Python :: 3.10
Classifier: Programming Language :: Python :: 3.11
Classifier: Programming Language :: Python :: 3.12
Requires-Dist: addict (>=2.4.0,<3.0.0)
Requires-Dist: bufbuild-protovalidate-protocolbuffers-python
Requires-Dist: bufbuild_protovalidate_grpc_python
Requires-Dist: colorama (>=0.4.6,<0.5.0)
Requires-Dist: detoxio-ai-api-protocolbuffers-python
Requires-Dist: detoxio_ai_api_grpc_python
Requires-Dist: dtx-apis-prompts-utils (>=0.2.0,<0.3.0)
Requires-Dist: dtx-assessment-api (>=0.10.1,<0.11.0)
Requires-Dist: googleapis_googleapis_grpc_python
Requires-Dist: googleapis_googleapis_protocolbuffers_python
Requires-Dist: gradio-client (>=1.5.1,<2.0.0)
Requires-Dist: grpcio
Requires-Dist: grpcio-tools
Requires-Dist: haralyzer (>=2.4.0,<3.0.0)
Requires-Dist: httpx
Requires-Dist: langchain-groq (>=0.2.0,<0.3.0)
Requires-Dist: langchain-openai (>=0.2.0,<0.3.0)
Requires-Dist: markdown (>=3.5.2,<4.0.0)
Requires-Dist: markdown-builder (>=0.1.2,<0.2.0)
Requires-Dist: networkx (>=3.3,<4.0)
Requires-Dist: openai (>=1.57.0,<2.0.0)
Requires-Dist: playwright (>=1.42.0,<2.0.0)
Requires-Dist: progress
Requires-Dist: retry
Requires-Dist: transformers (>=4.38.2,<5.0.0)
Requires-Dist: transitions (>=0.9.2,<0.10.0)
Requires-Dist: validators (>=0.23.2,<0.24.0)
